{
  "title": "Entity Resolution Classification Metrics",
  "timestamp": "2025-03-09 10:10:23",
  "metrics": {
    "precision": 1.0,
    "recall": 0.9004184815099496,
    "f1": 0.9476002157109473,
    "accuracy": 0.9498882585525185,
    "roc_auc": 0.9999182751141604,
    "confusion_matrix": {
      "true_negatives": 11559,
      "false_positives": 0,
      "false_negatives": 1166,
      "true_positives": 10543
    }
  },
  "feature_representations": {
    "standard": "Main feature columns contain StandardScaler values used for training",
    "raw": "Raw feature values in original range (e.g., [-1,1] for cosine similarity)",
    "normalized": "Domain-normalized feature values in [0,1] range"
  }
}